filecheck/__init__.py
filecheck/__main__.py
filecheck/compiler.py
filecheck/error.py
filecheck/finput.py
filecheck/help.py
filecheck/main.py
filecheck/matcher.py
filecheck/ops.py
filecheck/options.py
filecheck/parser.py
filecheck/preprocess.py
filecheck/py.typed
filecheck/regex.py
filecheck_ng-0.1.2.dist-info/LICENSE.md
filecheck_ng-0.1.2.dist-info/METADATA
filecheck_ng-0.1.2.dist-info/WHEEL
filecheck_ng-0.1.2.dist-info/entry_points.txt
filecheck_ng-0.1.2.dist-info/RECORD
