Metadata-Version: 2.1
Name: filecheck-ng
Version: 0.1.2
Summary: A Python-native clone of LLVMs FileCheck tool
Home-page: https://github.com/AntonLydike/filecheck
License: GPL-3.0-or-later
Keywords: tests,filecheck,llvm
Author: Anton Lydike
Author-email: me@antonlydike.de
Requires-Python: >=3.10,<4.0
Classifier: License :: OSI Approved :: GNU General Public License v3 or later (GPLv3+)
Classifier: Programming Language :: Python :: 3
Classifier: Programming Language :: Python :: 3.10
Classifier: Programming Language :: Python :: 3.11
Classifier: Programming Language :: Python :: 3.12
Project-URL: Repository, https://github.com/AntonLydike/filecheck
